re101/__init__.py
re101-0.4.0.dist-info/LICENSE
re101-0.4.0.dist-info/METADATA
re101-0.4.0.dist-info/WHEEL
re101-0.4.0.dist-info/top_level.txt
re101-0.4.0.dist-info/RECORD
