Metadata-Version: 1.2
Name: re101
Version: 0.4.0
Summary: A back-pocket regex cookbook
Home-page: https://github.com/bsolomon1124/re101
Author: Brad Solomon
Author-email: brad.solomon.1124@gmail.com
License: MIT
Keywords: regex,re,tokenizer,token
Platform: UNKNOWN
Classifier: License :: OSI Approved :: MIT License
Classifier: Operating System :: Unix
Classifier: Operating System :: POSIX
Classifier: Operating System :: Microsoft :: Windows
Classifier: Programming Language :: Python
Classifier: Programming Language :: Python :: 3
Classifier: Programming Language :: Python :: 3.4
Classifier: Programming Language :: Python :: 3.5
Classifier: Programming Language :: Python :: 3.6
Classifier: Programming Language :: Python :: 3.7
Classifier: Intended Audience :: Developers
Classifier: Natural Language :: English
Classifier: Topic :: Text Processing :: Linguistic
Classifier: Programming Language :: Python :: Implementation :: CPython
Requires-Python: >=3
